line_sticker_for_whatsapp/__about__.py
line_sticker_for_whatsapp/__init__.py
line_sticker_for_whatsapp/__main__.py
line_sticker_for_whatsapp/sticker.py
line_sticker_for_whatsapp/cli/__init__.py
line_sticker_for_whatsapp-0.0.1.dist-info/METADATA
line_sticker_for_whatsapp-0.0.1.dist-info/WHEEL
line_sticker_for_whatsapp-0.0.1.dist-info/entry_points.txt
line_sticker_for_whatsapp-0.0.1.dist-info/licenses/LICENSE.txt
line_sticker_for_whatsapp-0.0.1.dist-info/RECORD
