Metadata-Version: 2.1
Name: line-sticker-for-whatsapp
Version: 0.0.1
Summary: Download and convert LINE sticker pack into WhatsApp compatible format.
Project-URL: Documentation, https://github.com/Shivelight/line-sticker-for-whatsapp
Project-URL: Issues, https://github.com/Shivelight/line-sticker-for-whatsapp/issues
Project-URL: Source, https://github.com/Shivelight/line-sticker-for-whatsapp
Author-email: Shivelight <shivelight@tuta.io>
License-Expression: MIT
License-File: LICENSE.txt
Classifier: Development Status :: 4 - Beta
Classifier: Programming Language :: Python
Classifier: Programming Language :: Python :: 3.7
Classifier: Programming Language :: Python :: 3.8
Classifier: Programming Language :: Python :: 3.9
Classifier: Programming Language :: Python :: 3.10
Classifier: Programming Language :: Python :: 3.11
Classifier: Programming Language :: Python :: Implementation :: CPython
Classifier: Programming Language :: Python :: Implementation :: PyPy
Requires-Python: >=3.7
Requires-Dist: click
